[
  {
    "connectionString": "Server=.\\SQLEXPRESS;Database=CertificateAdministration_Life;Trusted_Connection=True",
    "outputDirectory": "C:\\dev\\SqlDumpSampleOutput",
    "fileNamePrefix": "0001_",
    "tableRequests": [
      {
        "name": "ValuationProcessing.Certificate",
        "includeIdentityInsert": true
      },
      {
        "name": "ValuationProcessing.Rider",
        "includeIdentityInsert": true
      }
    ]
  },
  {
    "connectionString": "Server=.\\SQLEXPRESS;Database=ERA_Administration;Trusted_Connection=True",
    "outputDirectory": "C:\\dev\\SqlDumpSampleOutput\\ERA_Administration",
    "fileNamePrefix": "0002_",
    "tableRequests": [
      {
        "name": "dbo.Product",
        "includeIdentityInsert": false
      }
    ]
  }
]